IBITTokenizer/__init__.py
IBITTokenizer/tokenizer.py
IBITTokenizer/resource/IBIT_TOKENIZER.json
IBITTokenizer-0.0.2.dist-info/METADATA
IBITTokenizer-0.0.2.dist-info/WHEEL
IBITTokenizer-0.0.2.dist-info/top_level.txt
IBITTokenizer-0.0.2.dist-info/RECORD
