Metadata-Version: 2.1
Name: IBITTokenizer
Version: 0.0.2
Summary: Tokenizer for Persian texts based on hazm
Author: MahdiGhaemi
Author-email: mahdighaemi123@email.com
Requires-Dist: tokenizers
